odoo/addons/project_task_stage_state/README.rst
odoo/addons/project_task_stage_state/__init__.py
odoo/addons/project_task_stage_state/__manifest__.py
odoo/addons/project_task_stage_state/demo/project_task_type_demo.xml
odoo/addons/project_task_stage_state/i18n/ar.po
odoo/addons/project_task_stage_state/i18n/bg.po
odoo/addons/project_task_stage_state/i18n/ca.po
odoo/addons/project_task_stage_state/i18n/de.po
odoo/addons/project_task_stage_state/i18n/el.po
odoo/addons/project_task_stage_state/i18n/el_GR.po
odoo/addons/project_task_stage_state/i18n/es.po
odoo/addons/project_task_stage_state/i18n/es_AR.po
odoo/addons/project_task_stage_state/i18n/es_CR.po
odoo/addons/project_task_stage_state/i18n/es_MX.po
odoo/addons/project_task_stage_state/i18n/es_PA.po
odoo/addons/project_task_stage_state/i18n/es_VE.po
odoo/addons/project_task_stage_state/i18n/fi.po
odoo/addons/project_task_stage_state/i18n/fr.po
odoo/addons/project_task_stage_state/i18n/fr_FR.po
odoo/addons/project_task_stage_state/i18n/gl.po
odoo/addons/project_task_stage_state/i18n/hr.po
odoo/addons/project_task_stage_state/i18n/hr_HR.po
odoo/addons/project_task_stage_state/i18n/hu.po
odoo/addons/project_task_stage_state/i18n/it.po
odoo/addons/project_task_stage_state/i18n/ja.po
odoo/addons/project_task_stage_state/i18n/lt.po
odoo/addons/project_task_stage_state/i18n/lv.po
odoo/addons/project_task_stage_state/i18n/mk.po
odoo/addons/project_task_stage_state/i18n/mn.po
odoo/addons/project_task_stage_state/i18n/nb.po
odoo/addons/project_task_stage_state/i18n/nb_NO.po
odoo/addons/project_task_stage_state/i18n/nl.po
odoo/addons/project_task_stage_state/i18n/nl_NL.po
odoo/addons/project_task_stage_state/i18n/pl.po
odoo/addons/project_task_stage_state/i18n/project_task_stage_state.pot
odoo/addons/project_task_stage_state/i18n/pt.po
odoo/addons/project_task_stage_state/i18n/pt_BR.po
odoo/addons/project_task_stage_state/i18n/pt_PT.po
odoo/addons/project_task_stage_state/i18n/ro.po
odoo_addon_project_task_stage_state-19.0.1.0.0.3.dist-info/METADATA
odoo_addon_project_task_stage_state-19.0.1.0.0.3.dist-info/WHEEL
odoo_addon_project_task_stage_state-19.0.1.0.0.3.dist-info/top_level.txt
odoo_addon_project_task_stage_state-19.0.1.0.0.3.dist-info/RECORD
