Metadata-Version: 2.1
Name: odoo-addon-project_task_stage_state
Version: 19.0.1.0.0.3
Requires-Dist: odoo==19.0.*
Summary: Restore State attribute removed from Project Stages in 8.0
Home-page: https://github.com/OCA/project
License: AGPL-3
Author: Daniel Reis, Odoo Community Association (OCA)
Author-email: support@odoo-community.org
Classifier: Programming Language :: Python
Classifier: Framework :: Odoo
Classifier: Framework :: Odoo :: 19.0
Classifier: License :: OSI Approved :: GNU Affero General Public License v3
